PyLuci/__init__.py
PyLuci/__main__.py
PyLuci/configs.py
PyLuci/exceptions.py
PyLuci/kynan.py
PyLuci/loader.py
PyLuci/version.py
PyLuci/_misc/__init__.py
PyLuci/_misc/_assistant.py
PyLuci/_misc/_decorators.py
PyLuci/_misc/_supporter.py
PyLuci/_misc/_wrappers.py
PyLuci/dB/__init__.py
PyLuci/dB/_core.py
PyLuci/dB/afk_db.py
PyLuci/dB/antiflood_db.py
PyLuci/dB/asst_fns.py
PyLuci/dB/asstcmd_db.py
PyLuci/dB/autoban_db.py
PyLuci/dB/blacklist_chat_db.py
PyLuci/dB/blacklist_db.py
PyLuci/dB/botchat_db.py
PyLuci/dB/broadcast_db.py
PyLuci/dB/ch_db.py
PyLuci/dB/dnd_db.py
PyLuci/dB/echo_db.py
PyLuci/dB/filestore_db.py
PyLuci/dB/filter_db.py
PyLuci/dB/forcesub_db.py
PyLuci/dB/gban_mute_db.py
PyLuci/dB/gcast_blacklist_db.py
PyLuci/dB/greetings_db.py
PyLuci/dB/logusers_db.py
PyLuci/dB/mute_db.py
PyLuci/dB/night_db.py
PyLuci/dB/notes_db.py
PyLuci/dB/nsfw_db.py
PyLuci/dB/pmpermit_db.py
PyLuci/dB/snips_db.py
PyLuci/dB/vc_sudos.py
PyLuci/dB/warn_db.py
PyLuci/fns/FastTelethon.py
PyLuci/fns/__init__.py
PyLuci/fns/admins.py
PyLuci/fns/executor.py
PyLuci/fns/gDrive.py
PyLuci/fns/google_image.py
PyLuci/fns/helper.py
PyLuci/fns/info.py
PyLuci/fns/misc.py
PyLuci/fns/tools.py
PyLuci/fns/ytdl.py
PyLuci/startup/BaseClient.py
PyLuci/startup/__init__.py
PyLuci/startup/_database.py
PyLuci/startup/_extra.py
PyLuci/startup/connections.py
PyLuci/startup/funcs.py
PyLuci/startup/loader.py
PyLuci/startup/utils.py
pyLuci-1.0.0.dist-info/LICENSE
pyLuci-1.0.0.dist-info/METADATA
pyLuci-1.0.0.dist-info/WHEEL
pyLuci-1.0.0.dist-info/top_level.txt
pyLuci-1.0.0.dist-info/RECORD
