Metadata-Version: 2.1
Name: pyLuci
Version: 1.0.0
Summary: A Secure and Powerful Python-Telethon Based Library For Luci UserBot.
Home-page: https://github.com/jonesroot/py-luci
Author: jonesroot
Author-email: cosmospanas70@gmail.com
License: GNU AFFERO GENERAL PUBLIC LICENSE (v3)
Project-URL: Bug Tracker, https://github.com/jonesroot/py-luci/issues
Project-URL: Documentation, https://ultroid.tech
Project-URL: Source Code, https://github.com/jonesroot/py-luci
Classifier: Programming Language :: Python :: 3
Classifier: Programming Language :: Python :: 3.8
Classifier: Programming Language :: Python :: 3.9
Classifier: Programming Language :: Python :: 3.10
Classifier: Programming Language :: Python :: 3.11
Classifier: Programming Language :: Python :: 3.12
Classifier: License :: OSI Approved :: GNU General Public License v3 (GPLv3)
Classifier: Operating System :: OS Independent
Requires-Python: >3.7, <3.12
License-File: LICENSE
Requires-Dist: pymongo
Requires-Dist: python-decouple
Requires-Dist: python-dotenv
